{"version":"6.1","id":"cmgzekoww000qs51ahvqiv4rq","name":"abc","events":[{"id":"l42298er4j0eld98k51sbvim","graphCoordinates":{"x":0,"y":0},"type":"start"}],"groups":[],"edges":[],"variables":[],"theme":{},"selectedThemeTemplateId":null,"settings":{},"createdAt":"2025-10-20T17:22:03.680Z","updatedAt":"2025-10-20T17:22:07.259Z","icon":null,"folderId":null,"publicId":"abc-vqiv4rq","customDomain":null,"workspaceId":"cm7dahbq50001c7m972ujn7jt","resultsTablePreferences":null,"isArchived":false,"isClosed":false,"whatsAppCredentialsId":null,"riskLevel":null}